msQuantum/__init__.py
msQuantum-0.1.0.dev0.dist-info/METADATA
msQuantum-0.1.0.dev0.dist-info/WHEEL
msQuantum-0.1.0.dev0.dist-info/top_level.txt
msQuantum-0.1.0.dev0.dist-info/RECORD
