Metadata-Version: 2.1
Name: msQuantum
Version: 0.1.0.dev0
Summary: msQuantum
Home-page: https://github.com/IsotopeC/msQuantum
Author: Calvin Peters
Author-email: calvin.isotope@gmail.com
License: UNKNOWN
Platform: UNKNOWN
Requires-Python: >3.6
